UTemplates/__init__.py
UTemplates/configuration.py
UTemplates/general_base.py
UTemplates/rendering.py
UTemplates/utils.py
UTemplates/html_specific/__init__.py
UTemplates/html_specific/base.py
UTemplates/html_specific/boilderplate_pages.py
UTemplates/html_specific/declarations.py
UTemplates/html_specific/tags/__init__.py
UTemplates/html_specific/tags/a_tags.py
UTemplates/html_specific/tags/b_tags.py
UTemplates/html_specific/tags/c_tags.py
UTemplates/html_specific/tags/d_tags.py
UTemplates/html_specific/tags/e_tags.py
UTemplates/html_specific/tags/f_tags.py
UTemplates/html_specific/tags/general_tags.py
UTemplates/html_specific/tags/h_tags.py
UTemplates/html_specific/tags/i_tags.py
UTemplates/html_specific/tags/k_tags.py
UTemplates/html_specific/tags/l_tags.py
UTemplates/html_specific/tags/m_tags.py
UTemplates/html_specific/tags/n_tags.py
UTemplates/html_specific/tags/o_tags.py
UTemplates/html_specific/tags/p_tags.py
UTemplates/html_specific/tags/q_tags.py
UTemplates/html_specific/tags/r_tags.py
UTemplates/html_specific/tags/s_tags.py
UTemplates/html_specific/tags/t_tags.py
UTemplates/html_specific/tags/u_tags.py
UTemplates/html_specific/tags/v_tags.py
UTemplates/html_specific/tags/w_tags.py
UTemplates/integrations/__init__.py
UTemplates/integrations/django_integrations.py
utemplates-0.26.dist-info/LICENSE.md
utemplates-0.26.dist-info/METADATA
utemplates-0.26.dist-info/WHEEL
utemplates-0.26.dist-info/top_level.txt
utemplates-0.26.dist-info/RECORD
